jacobi_camera_driver/__init__.py
jacobi_camera_driver/camera_driver.py
jacobi_simulated_camera_driver/__init__.py
jacobi_simulated_camera_driver/simulated_camera_driver.py
jacobi_simulated_camera_driver-0.1.0.dist-info/LICENSE
jacobi_simulated_camera_driver-0.1.0.dist-info/METADATA
jacobi_simulated_camera_driver-0.1.0.dist-info/WHEEL
jacobi_simulated_camera_driver-0.1.0.dist-info/top_level.txt
jacobi_simulated_camera_driver-0.1.0.dist-info/RECORD
