Metadata-Version: 2.1
Name: jacobi-simulated-camera-driver
Version: 0.1.0
Summary: Driver for simulated camera.
Author-email: Lars Berscheid <lars.berscheid@jacobirobotics.com>, Andreas ten Pas <andreas.tenpas@jacobirobotics.com>
License: Copyright (c) 2024 Jacobi Robotics Inc.
Project-URL: homepage, https://www.jacobirobotics.com
Project-URL: documentation, https://docs.jacobirobotics.com
Keywords: robotics,computer-vision
Classifier: Development Status :: 3 - Alpha
Classifier: Intended Audience :: Science/Research
Classifier: Topic :: Scientific/Engineering
Classifier: License :: Other/Proprietary License
Classifier: Programming Language :: Python
Requires-Python: >=3.10
License-File: LICENSE
Requires-Dist: jacobi-vision
